README.rst
setup.py
qda_modelos/__init__.py
qda_modelos/chlorophylla.py
qda_modelos/cyanobacteria.py
qda_modelos/macrophytes.py
qda_modelos/reservoir_water_quality_index.py
qda_modelos/total_suspended_solids_turbidity.py
qda_modelos/trophic_state_index.py
qda_modelos/water_transparency.py
qda_modelos.egg-info/PKG-INFO
qda_modelos.egg-info/SOURCES.txt
qda_modelos.egg-info/dependency_links.txt
qda_modelos.egg-info/requires.txt
qda_modelos.egg-info/top_level.txt