Metadata-Version: 2.1
Name: qda-modelos
Version: 1.1.2
Summary: Implement bio-optic models to evaluate water quality indexes with satellite images.
Home-page: https://github.com/fundacaocerti/qda_modelos
Author: CERTI Foundation
Author-email: qda-pypi@certi.org.br
License: BSD
Download-URL: https://github.com/fundacaocerti/qda_modelos/archive/v1.1.2.tar.gz
Keywords: bio-optic models,water quality,indexes,satellite image,reservoir,lake,water,remote sensing
Platform: UNKNOWN
Classifier: Programming Language :: Python :: 3
Classifier: License :: OSI Approved :: BSD License
Classifier: Operating System :: OS Independent
